LICENSE
MANIFEST.in
README.md
__init__.py
renkler.py
setup.py
renk.egg-info/PKG-INFO
renk.egg-info/SOURCES.txt
renk.egg-info/dependency_links.txt
renk.egg-info/not-zip-safe
renk.egg-info/top_level.txt