Metadata-Version: 1.0
Name: renk
Version: 0.0.1
Summary: pythonla kullanılmak için hazirlanmış türkçe terminal renkleri
Home-page: https://github.com/bksec/renkler
Author: Berkay Küçük
Author-email: berkay@berkaykucuk.com.tr
License: MIT License
Keywords: renkler,colours,renk
Platform: UNKNOWN
